beaucli/__init__.py
beaucli-0.0.dev3.dist-info/LICENSE
beaucli-0.0.dev3.dist-info/METADATA
beaucli-0.0.dev3.dist-info/WHEEL
beaucli-0.0.dev3.dist-info/top_level.txt
beaucli-0.0.dev3.dist-info/RECORD
