Metadata-Version: 2.1
Name: beaucli
Version: 0.0.dev3
Summary: a tool for making your cli applications more colorful!
Home-page: https://github.com/memesterhub/beaucli
Author: Hussein Amine
Author-email: husseinraedamine56@gmail.com
License: UNKNOWN
Platform: UNKNOWN
Classifier: Programming Language :: Python :: 3
Classifier: Programming Language :: Python :: 2
Classifier: License :: OSI Approved :: MIT License
Classifier: Operating System :: OS Independent
Requires-Python: >=2.7
